[
  {
    "name": "branchingQuestion",
    "type": "group",
    "widget": "branchingQuestion",
    "label": "Branching Question Editor",
    "importance": "high",
    "fields": [
      {
        "name": "question",
        "type": "text",
        "importance": "medium",
        "widget": "html",
        "label": "Question",
        "enterMode": "p",
        "tags": [
          "strong",
          "em",
          "sub",
          "sup",
          "h2",
          "h3"
        ]
      },
      {
        "name": "alternatives",
        "type": "list",
        "importance": "high",
        "label": "Available alternatives",
        "entity": "alternative",
        "min": 2,
        "defaultNum": 2,
        "field": {
          "name": "answer",
          "type": "group",
          "label": "Alternative",
          "importance": "high",
          "fields": [
            {
              "name": "text",
              "type": "text",
              "importance": "medium",
              "label": "Text"
            },
            {
              "name": "nextContentId",
              "type": "number",
              "label": "Next Content ID (end screens are defined by negative numbers)",
              "importance": "high"
            },
            {
              "name": "feedback",
              "type": "group",
              "label": "Feedback",
              "fields": [
                {
                  "name": "title",
                  "type": "text",
                  "label": "Feedback Text Title",
                  "optional": true
                },
                {
                  "name": "subtitle",
                  "type": "text",
                  "label": "Feedback Text",
                  "optional": true
                },
                {
                  "name": "image",
                  "type": "image",
                  "label": "Feedback image",
                  "optional": true
                },
                {
                  "name": "endScreenScore",
                  "type": "number",
                  "label": "Score for this scenario",
                  "description": "The number of points that will be given for ending up with this scenario",
                  "default": 0,
                  "optional": true
                }
              ]
            }
          ]
        }
      },
      {
        "name": "proceedButtonLabel",
        "label": "Proceed button label",
        "type": "text",
        "default": "Proceed",
        "common": true
      }
    ]
  }
]
